forceatlas2/__init__.py
forceatlas2/ext/forceatlas2.jar
forceatlas2/ext/gephi-toolkit-0.9.2-all.jar
forceatlas2_python-1.1.dist-info/LICENSE
forceatlas2_python-1.1.dist-info/METADATA
forceatlas2_python-1.1.dist-info/WHEEL
forceatlas2_python-1.1.dist-info/top_level.txt
forceatlas2_python-1.1.dist-info/RECORD
